key_stroke/__init__.py
key_stroke/key_stroke.py
key_stroke-1.3.1.dist-info/METADATA
key_stroke-1.3.1.dist-info/WHEEL
key_stroke-1.3.1.dist-info/licenses/LICENSE
key_stroke-1.3.1.dist-info/RECORD
