Metadata-Version: 2.4
Name: key_stroke
Version: 1.3.1
Summary: The python key stroke module to capture a key stroke and do something useful (e.g. terminating an application). It works an all platforms
Project-URL: Homepage, https://github.com/chriesibaum/key_stroke
Author-email: Thomas <thomas@chriesibaum.com>
License: tbd.
License-File: LICENSE
Classifier: License :: OSI Approved :: MIT License
Classifier: Operating System :: OS Independent
Classifier: Programming Language :: Python :: 3
Requires-Python: >=3.8
Requires-Dist: msvcrt; platform_system == 'windows'
Requires-Dist: select; platform_system == 'linux'
Requires-Dist: termios; platform_system == 'linux'
Requires-Dist: tty; platform_system == 'linux'
